Workbook

Sheet Q4 Overview
B2: Image Group International | Social Media Calendar Q4 2026
B3: Mock plan for portfolio purposes. Not an official IGI document. Episode numbers, links, figures and client details are placeholders to confirm.
B5: Posting cadence
B6: Day | C6: What goes out
B7: Tuesday | C7: Thought leadership carousel on LinkedIn IGI, repurposed to Instagram
B8: Thursday | C8: Podcast episode carousel on LinkedIn IGI, included in the weekly newsletter
B9: Monthly | C9: Long-form blog article (see Content Briefs tab)
B11: Content pillar mix
B12: Pillar | C12: Target share | D12: Posts planned | E12: Actual share | F12: Variance
B13: Authentic Personal Branding | C13: 0.3 | D13: =COUNTIF(Jon!$F:$F,B13) -> 9 | E13: =IF($D$18=0,0,D13/$D$18) -> 0.34615385 | F13: =E13-C13 -> 0.046153846
B14: Reputation & Digital Presence | C14: 0.2 | D14: =COUNTIF(Jon!$F:$F,B14) -> 5 | E14: =IF($D$18=0,0,D14/$D$18) -> 0.19230769 | F14: =E14-C14 -> -0.0076923077
B15: Executive Presence & Image | C15: 0.2 | D15: =COUNTIF(Jon!$F:$F,B15) -> 5 | E15: =IF($D$18=0,0,D15/$D$18) -> 0.19230769 | F15: =E15-C15 -> -0.0076923077
B16: Leadership & Communication | C16: 0.15 | D16: =COUNTIF(Jon!$F:$F,B16) -> 4 | E16: =IF($D$18=0,0,D16/$D$18) -> 0.15384615 | F16: =E16-C16 -> 0.0038461538
B17: Seasonal & Community | C17: 0.15 | D17: =COUNTIF(Jon!$F:$F,B17) -> 3 | E17: =IF($D$18=0,0,D17/$D$18) -> 0.11538462 | F17: =E17-C17 -> -0.034615385
B18: Total | C18: =SUM(C13:C17) -> 1 | D18: =SUM(D13:D17) -> 26
B19: Blue figures are editable targets. Counts update from the Jon tab.
B21: Posts by month and status
B22: Status | C22: October | D22: November | E22: December | F22: Total
B23: Idea | C23: =COUNTIFS(Jon!$I:$I,$B23,Jon!$C:$C,">="&DATE(2026,10,1),Jon!$C:$C,"<="&DATE(2026,10,31)) -> 0 | D23: =COUNTIFS(Jon!$I:$I,$B23,Jon!$C:$C,">="&DATE(2026,11,1),Jon!$C:$C,"<="&DATE(2026,11,30)) -> 0 | E23: =COUNTIFS(Jon!$I:$I,$B23,Jon!$C:$C,">="&DATE(2026,12,1),Jon!$C:$C,"<="&DATE(2026,12,31)) -> 0 | F23: =SUM(C23:E23) -> 0
B24: Drafted | C24: =COUNTIFS(Jon!$I:$I,$B24,Jon!$C:$C,">="&DATE(2026,10,1),Jon!$C:$C,"<="&DATE(2026,10,31)) -> 0 | D24: =COUNTIFS(Jon!$I:$I,$B24,Jon!$C:$C,">="&DATE(2026,11,1),Jon!$C:$C,"<="&DATE(2026,11,30)) -> 8 | E24: =COUNTIFS(Jon!$I:$I,$B24,Jon!$C:$C,">="&DATE(2026,12,1),Jon!$C:$C,"<="&DATE(2026,12,31)) -> 9 | F24: =SUM(C24:E24) -> 17
B25: In Design | C25: =COUNTIFS(Jon!$I:$I,$B25,Jon!$C:$C,">="&DATE(2026,10,1),Jon!$C:$C,"<="&DATE(2026,10,31)) -> 0 | D25: =COUNTIFS(Jon!$I:$I,$B25,Jon!$C:$C,">="&DATE(2026,11,1),Jon!$C:$C,"<="&DATE(2026,11,30)) -> 0 | E25: =COUNTIFS(Jon!$I:$I,$B25,Jon!$C:$C,">="&DATE(2026,12,1),Jon!$C:$C,"<="&DATE(2026,12,31)) -> 0 | F25: =SUM(C25:E25) -> 0
B26: Awaiting Jon's Approval | C26: =COUNTIFS(Jon!$I:$I,$B26,Jon!$C:$C,">="&DATE(2026,10,1),Jon!$C:$C,"<="&DATE(2026,10,31)) -> 4 | D26: =COUNTIFS(Jon!$I:$I,$B26,Jon!$C:$C,">="&DATE(2026,11,1),Jon!$C:$C,"<="&DATE(2026,11,30)) -> 0 | E26: =COUNTIFS(Jon!$I:$I,$B26,Jon!$C:$C,">="&DATE(2026,12,1),Jon!$C:$C,"<="&DATE(2026,12,31)) -> 0 | F26: =SUM(C26:E26) -> 4
B27: Scheduled | C27: =COUNTIFS(Jon!$I:$I,$B27,Jon!$C:$C,">="&DATE(2026,10,1),Jon!$C:$C,"<="&DATE(2026,10,31)) -> 5 | D27: =COUNTIFS(Jon!$I:$I,$B27,Jon!$C:$C,">="&DATE(2026,11,1),Jon!$C:$C,"<="&DATE(2026,11,30)) -> 0 | E27: =COUNTIFS(Jon!$I:$I,$B27,Jon!$C:$C,">="&DATE(2026,12,1),Jon!$C:$C,"<="&DATE(2026,12,31)) -> 0 | F27: =SUM(C27:E27) -> 5
B28: Published | C28: =COUNTIFS(Jon!$I:$I,$B28,Jon!$C:$C,">="&DATE(2026,10,1),Jon!$C:$C,"<="&DATE(2026,10,31)) -> 0 | D28: =COUNTIFS(Jon!$I:$I,$B28,Jon!$C:$C,">="&DATE(2026,11,1),Jon!$C:$C,"<="&DATE(2026,11,30)) -> 0 | E28: =COUNTIFS(Jon!$I:$I,$B28,Jon!$C:$C,">="&DATE(2026,12,1),Jon!$C:$C,"<="&DATE(2026,12,31)) -> 0 | F28: =SUM(C28:E28) -> 0
B29: Total | C29: =SUM(C23:C28) -> 9 | D29: =SUM(D23:D28) -> 8 | E29: =SUM(E23:E28) -> 9 | F29: =SUM(F23:F28) -> 26
B32: Key dates this quarter
B33: Occasion | C33: Date | D33: Tie-in
B34: Mental Health Month | C34: 1 to 31 Oct | D34: 8 Oct podcast
B35: World Mental Health Day | C35: 10 Oct | D35: 8 Oct podcast
B36: Derby Day | C36: 31 Oct | D36: 27 Oct carousel, 29 Oct podcast
B37: Melbourne Cup (public holiday) | C37: 3 Nov | D37: 3 Nov post, pre-scheduled
B38: Movember | C38: 1 to 30 Nov | D38: 5 Nov podcast
B39: World Kindness Day | C39: 13 Nov | D39: 10 Nov carousel
B40: Global Entrepreneurship Week | C40: Mid Nov (confirm) | D40: 17 Nov carousel, 19 Nov podcast
B41: International Men's Day | C41: 19 Nov | D41: 19 Nov podcast
B42: Black Friday | C42: 27 Nov | D42: 24 Nov carousel, 26 Nov podcast
B43: Festive party season | C43: Dec | D43: 1 Dec carousel, 3 Dec podcast
B44: Christmas | C44: 24 to 25 Dec | D44: 24 Dec greeting
B45: New Year's Eve | C45: 31 Dec | D45: 31 Dec encore episode

Sheet Jon
A1: Post/Podcast | B1: Carousels | C1: Date | D1: Platform | E1: Content to go with Carousels | F1: Content Pillar | G1: Key Date Tie-in | H1: Carousel Slide Outline | I1: Status | J1: Notes
A2: Finishing the Year With Intent: Your Q4 Brand Audit | B2: [Canva link] | C2: 46296 | D2: Carousel of Podcast [Ep. #] LinkedIn IGI + Newsletter | E2: New Podcast Episode 🎧 The final quarter is when decision makers quietly decide who they want to work with next year. Is your personal brand ready for that conversation? In this episode I walk through a simple Q4 brand audit for CEOs, executives and entrepreneurs. We look at how you show up online, how you show up in the room, and whether the two tell the same story. Learn how to spot the gaps between how you see yourself and how others experience you, and what to fix first before planning season begins. 👉 Listen now [Insert podcast link] #PersonalBranding #Leadership #BrandAudit #JonMichail | F2: Authentic Personal Branding | G2: Start of Q4 | H2: S1 Episode title + cover, S2 Hook question, S3-S5 Three key takeaways, S6 Pull quote from Jon, S7 Listen now CTA | I2: Scheduled | J2: Pairs with October blog (see Content Briefs).
A3: Visibility Is Not the Same as Authority | B3: [Canva link] | C3: 46301 | D3: Carousel for LinkedIn IGI + Instagram | E3: Being seen is not the same as being trusted. Many professionals post often, speak at events and grow their following, yet still struggle to turn attention into influence. That is the gap between visibility and authority. Authority comes from clarity about what you stand for, positioning that makes you the obvious choice, and consistency that builds trust over time. Swipe through to see where your personal brand sits today. #AuthorityPersonalBranding #PersonalBranding #Leadership #Influence | F3: Authentic Personal Branding | H3: S1 Visibility ≠ Authority, S2 The gap explained, S3 Clarity, S4 Positioning, S5 Consistency, S6 Self-check question, S7 Follow IGI | I3: Scheduled | J3: Uses IGI's Authority Personal Branding™ framing.
A4: Presence Under Pressure: Wellbeing and Your Personal Brand | B4: [Canva link] | C4: 46303 | D4: Carousel of Podcast [Ep. #] LinkedIn IGI + Newsletter | E4: October is Mental Health Month, and this week's episode is one I care deeply about. We often talk about personal branding as something external. Your image, your profile, your voice. But presence starts on the inside. When you are running on empty, people notice it in your energy, your decisions and your reliability long before you do. In this episode I share how leaders can protect their wellbeing and their reputation at the same time, and why sustainable visibility beats burnout every time. If you or someone you know is struggling, please reach out to Beyond Blue on 1300 22 4636 or Lifeline on 13 11 14. 🎧 Listen now [Insert podcast link] #MentalHealthMonth #Leadership #PersonalBranding #Wellbeing | F4: Leadership & Communication | G4: Mental Health Month (Oct); World Mental Health Day (10 Oct) | H4: S1 Episode title + cover, S2 Hook question, S3-S5 Three key takeaways, S6 Pull quote from Jon, S7 Listen now CTA | I4: Scheduled | J4: Verify helpline numbers before publishing.
A5: 6 LinkedIn Profile Fixes That Take Under an Hour | B5: [Canva link] | C5: 46308 | D5: Carousel for LinkedIn IGI + Instagram | E5: Your LinkedIn profile is often your first handshake. You do not need a full rebrand to make a stronger impression. These six fixes take under an hour and can change how decision makers see you straight away. Update your headshot, rewrite your headline, sharpen your About section, use the Featured section, refresh your banner and ask for one meaningful recommendation. Which one will you tackle first? Tell us in the comments 👇 #LinkedInTips #PersonalBranding #ProfessionalGrowth #DigitalPresence | F5: Reputation & Digital Presence | H5: S1 Title, S2 Headshot, S3 Headline, S4 About section, S5 Featured, S6 Banner, S7 Recommendations, S8 Comment CTA | I5: Scheduled
A6: Your LinkedIn Headline Is a Positioning Statement | B6: [Canva link] | C6: 46310 | D6: Carousel of Podcast [Ep. #] LinkedIn IGI + Newsletter | E6: Is your LinkedIn headline just your job title? If so, you are leaving your most valuable piece of digital real estate empty. Your headline follows you into every comment, search result and connection request. It is often the first thing a decision maker reads about you. In this episode I break down how to turn your headline into a clear positioning statement that says who you help, how you help them and why you are the right person to do it. 🎧 Tune in and then tell me, what does your headline say about you? [Insert podcast link] #LinkedInTips #PersonalBranding #Positioning #ProfessionalGrowth | F6: Reputation & Digital Presence | H6: S1 Episode title + cover, S2 Hook question, S3-S5 Three key takeaways, S6 Pull quote from Jon, S7 Listen now CTA | I6: Scheduled | J6: Follows on from 13 Oct carousel.
A7: A Crisis Doesn't Build Your Reputation. It Reveals It. | B7: [Canva link] | C7: 46315 | D7: Carousel for LinkedIn IGI + Instagram | E7: A crisis does not build your reputation. It reveals it. The leaders who navigate difficult moments well are rarely improvising. They have clear values, trusted relationships and a plan for how they will communicate before anything goes wrong. Swipe through for four principles of reputation resilience every executive should have in place today, not when the headlines hit. #ReputationManagement #CrisisCommunication #Leadership #TrustBuilding | F7: Reputation & Digital Presence | H7: S1 Title, S2 Why preparation matters, S3-S6 Four resilience principles, S7 Book a reputation review CTA | I7: Awaiting Jon's Approval
A8: Reputation Is What They Say When You Leave the Room | B8: [Canva link] | C8: 46317 | D8: Carousel of Podcast [Ep. #] LinkedIn IGI + Newsletter | E8: Your reputation is not what you say about yourself. It is what others believe when you are not in the room. In this episode I explore how perception shapes the decisions made about you, from promotions and board seats to partnerships and investment. We look at the signals people pick up on, the stories that travel without you, and how to take ownership of the narrative with clarity and consistency. Reputation is built slowly and lost quickly. The good news is that it can be designed. 🎧 Listen now [Insert podcast link] #Reputation #PersonalBranding #Leadership #TrustBuilding | F8: Reputation & Digital Presence | H8: S1 Episode title + cover, S2 Hook question, S3-S5 Three key takeaways, S6 Pull quote from Jon, S7 Listen now CTA | I8: Awaiting Jon's Approval | J8: Echoes the podcast's own tagline for brand consistency.
A9: Race Day Is a Networking Day | B9: [Canva link] | C9: 46322 | D9: Carousel for LinkedIn IGI + Instagram | E9: Derby Day and Cup Day are almost here. For many Melbourne professionals, race day is really a networking day in a very good outfit. Your appearance sends a message before you say a word. Swipe through for our corporate marquee guide, covering dress codes, fabrics and colours for spring, footwear that survives the lawn and the etiquette that keeps you remembered for the right reasons. #SpringRacingCarnival #MelbourneCup #ImageConsulting #BusinessEtiquette | F9: Executive Presence & Image | G9: Spring Racing Carnival (Derby Day 31 Oct, Melbourne Cup 3 Nov) | H9: S1 Title, S2 Decoding the dress code, S3 Spring fabrics and colours, S4 Footwear on grass, S5 Marquee etiquette, S6 Save for race day CTA | I9: Awaiting Jon's Approval | J9: Use licence-free race day imagery only.
A10: Social Capital: Turning Events Into Relationships | B10: [Canva link] | C10: 46324 | D10: Carousel of Podcast [Ep. #] LinkedIn IGI + Newsletter | E10: Spring Racing season is here, and for many professionals the corporate marquee is as much a networking room as a celebration. In this episode I talk about building social capital at events without making every conversation transactional. How to prepare, how to be memorable for the right reasons, and how to follow up in a way that turns a pleasant chat into a genuine relationship. Whether it is Derby Day, a gala dinner or an industry breakfast, the principles are the same. 🎧 Listen now [Insert podcast link] #Networking #SocialCapital #PersonalBranding #MelbourneBusiness | F10: Leadership & Communication | G10: Spring Racing Carnival | H10: S1 Episode title + cover, S2 Hook question, S3-S5 Three key takeaways, S6 Pull quote from Jon, S7 Listen now CTA | I10: Awaiting Jon's Approval
A11: Happy Cup Day, Melbourne | B11: [Canva link] | C11: 46329 | D11: Carousel for LinkedIn IGI + Instagram | E11: Happy Cup Day, Melbourne 🏇 Whether you are in a corporate marquee, at a backyard sweep or watching from the office, one reminder from us today. Your behaviour is part of your brand, and people remember how you made them feel long after they forget what you wore. Enjoy the day, celebrate well and look after each other. #MelbourneCup #CupDay #PersonalBranding #Melbourne | F11: Seasonal & Community | G11: Melbourne Cup (3 Nov, Melbourne public holiday) | H11: Single static graphic or 3-slide carousel, S1 Happy Cup Day, S2 Your behaviour is your brand, S3 Celebrate well | I11: Drafted | J11: Public holiday. Pre-schedule the day before.
A12: Men, Image and Wellbeing: What Movember Teaches Us About Presence | B12: [Canva link] | C12: 46331 | D12: Carousel of Podcast [Ep. #] LinkedIn IGI + Newsletter | E12: Movember is here, and it is a timely reminder that how men look after themselves shows up in how they lead. In this episode I talk openly about image, grooming and wellbeing for men in business. We cover why taking care of your presence is not vanity, how self-care builds confidence, and why the strongest leaders are the ones willing to check in on themselves and others. 🎧 Listen now [Insert podcast link] If you are growing a mo this month, we would love to see it. Share your progress in the comments. #Movember #MensHealth #Leadership #PersonalBranding | F12: Executive Presence & Image | G12: Movember (Nov) | H12: S1 Episode title + cover, S2 Hook question, S3-S5 Three key takeaways, S6 Pull quote from Jon, S7 Listen now CTA | I12: Drafted
A13: Kindness Is an Underrated Brand Asset | B13: [Canva link] | C13: 46336 | D13: Carousel for LinkedIn IGI + Instagram | E13: This Friday is World Kindness Day, and we think kindness deserves more credit in business. Some of the most respected leaders share one quality. They make people feel valued. Kindness builds loyalty, strengthens teams and shapes a reputation that competitors cannot copy. Swipe through for five small acts of kindness that leave a lasting impression at work. Then tag someone whose kindness shaped your career 👇 #WorldKindnessDay #Leadership #PersonalBranding #WorkplaceCulture | F13: Leadership & Communication | G13: World Kindness Day (13 Nov) | H13: S1 Title, S2 Why kindness is strategic, S3-S7 Five small acts, S8 Tag someone CTA | I13: Drafted
A14: On Camera, On Brand: Executive Presence in a Hybrid World | B14: [Canva link] | C14: 46338 | D14: Carousel of Podcast [Ep. #] LinkedIn IGI + Newsletter | E14: So many professional first impressions now happen through a screen. Are you as credible on camera as you are in the room? In this episode I share practical ways to carry your executive presence into video calls, virtual panels and recorded content. We cover lighting, framing, voice, attire and the small habits that quietly undermine your authority online. Hybrid work is here to stay. Your presence needs to work in both worlds. 🎧 Listen now [Insert podcast link] #ExecutivePresence #HybridWork #PersonalBranding #Communication | F14: Executive Presence & Image | H14: S1 Episode title + cover, S2 Hook question, S3-S5 Three key takeaways, S6 Pull quote from Jon, S7 Listen now CTA | I14: Drafted | J14: Pairs with November blog (see Content Briefs).
A15: Investors Buy the Founder Before the Business | B15: [Canva link] | C15: 46343 | D15: Carousel for LinkedIn IGI + Instagram | E15: Before investors back a business, they back the founder. Your pitch deck may explain the opportunity, but your presence, credibility and track record answer the question every investor is really asking. Can I trust this person with my money? Swipe through for five ways founders can strengthen their personal brand ahead of their next raise. #Founders #Startups #PersonalBranding #GEW2026 | F15: Authentic Personal Branding | G15: Global Entrepreneurship Week (mid Nov) | H15: S1 Title, S2 The real investor question, S3-S7 Five founder brand moves, S8 Follow IGI | I15: Drafted | J15: Confirm GEW 2026 dates and hashtag.
A16: Founder-Led Branding: When Your Name Is on the Door | B16: [Canva link] | C16: 46345 | D16: Carousel of Podcast [Ep. #] LinkedIn IGI + Newsletter | E16: It is Global Entrepreneurship Week, and this episode is for every founder who has ever wondered whether they really need a personal brand. The short answer is yes. Customers, investors and future hires are assessing you long before they assess your product. Your credibility becomes the company's credibility. In this episode I explore how founders can build a personal brand that strengthens the business rather than competing with it, and how to stay authentic while your profile grows. 🎧 Listen now [Insert podcast link] #Entrepreneurship #FounderBrand #PersonalBranding #GEW2026 | F16: Authentic Personal Branding | G16: Global Entrepreneurship Week; International Men's Day (19 Nov) | H16: S1 Episode title + cover, S2 Hook question, S3-S5 Three key takeaways, S6 Pull quote from Jon, S7 Listen now CTA | I16: Drafted | J16: Confirm GEW 2026 dates.
A17: If Your Only Differentiator Is Price, You Don't Have a Brand | B17: [Canva link] | C17: 46350 | D17: Carousel for LinkedIn IGI + Instagram | E17: If your only differentiator is price, you do not have a brand. You have a discount. This Black Friday week, we are making the case for competing on value instead. Swipe through to see how clear positioning, visible expertise and a strong reputation allow you to charge what you are worth, with confidence. #Branding #PremiumPositioning #PersonalBranding #BlackFriday | F17: Authentic Personal Branding | G17: Black Friday (27 Nov) | H17: S1 Title, S2 Price vs value, S3 Clear positioning, S4 Visible expertise, S5 Strong reputation, S6 Book a consultation CTA | I17: Drafted
A18: Premium Positioning: Why Discounting Yourself Costs More | B18: [Canva link] | C18: 46352 | D18: Carousel of Podcast [Ep. #] LinkedIn IGI + Newsletter | E18: Tomorrow is Black Friday, and everything seems to be on sale. Your expertise should not be. In this episode I unpack premium positioning for consultants, advisers and leaders. Why competing on price erodes trust, how to communicate value with confidence, and what authority looks like when you stop apologising for your fees. 🎧 Listen now [Insert podcast link] #PremiumPositioning #PersonalBranding #BusinessGrowth #Authority | F18: Authentic Personal Branding | G18: Black Friday (27 Nov) | H18: S1 Episode title + cover, S2 Hook question, S3-S5 Three key takeaways, S6 Pull quote from Jon, S7 Listen now CTA | I18: Drafted
A19: Christmas Party Dress Codes Decoded | B19: [Canva link] | C19: 46357 | D19: Carousel for LinkedIn IGI + Instagram | E19: Smart casual. Cocktail. Festive. What do they actually mean? Christmas party invitations are rolling in, and dress codes are not always clear. Swipe through for our simple guide to getting it right, so you look polished, feel comfortable and stay on brand all season. #ChristmasParty #DressCode #ImageConsulting #PersonalStyle | F19: Executive Presence & Image | G19: Festive party season | H19: S1 Title, S2 Smart casual, S3 Business casual, S4 Cocktail, S5 Festive, S6 Save for later CTA | I19: Drafted
A20: Festive Season Etiquette: The Office Party and Your Reputation | B20: [Canva link] | C20: 46359 | D20: Carousel of Podcast [Ep. #] LinkedIn IGI + Newsletter | E20: The office party lasts one night. The stories can last all year. As the festive season kicks off, this episode covers the etiquette every professional should keep in mind. From dress codes and drinks to what ends up on social media, I share how to enjoy the celebrations while protecting the reputation you have worked hard to build. 🎧 Listen now [Insert podcast link] #Etiquette #Reputation #PersonalBranding #WorkplaceCulture | F20: Reputation & Digital Presence | G20: Festive party season | H20: S1 Episode title + cover, S2 Hook question, S3-S5 Three key takeaways, S6 Pull quote from Jon, S7 Listen now CTA | I20: Drafted
A21: Don't Wait for Your Performance Review to Tell Your Story | B21: [Canva link] | C21: 46364 | D21: Carousel for LinkedIn IGI + Instagram | E21: Do not wait for your performance review to tell your story. The professionals who progress fastest make their contributions visible throughout the year, not just in December. Swipe through for four ways to document your wins, communicate your impact and make sure the right people know what you have achieved. #CareerGrowth #PersonalBranding #PerformanceReview #Leadership | F21: Leadership & Communication | G21: Year-end reviews | H21: S1 Title, S2-S5 Four visibility habits, S6 Comment with your biggest 2026 win | I21: Drafted
A22: Reinvention: Evolving Your Career Image for the Year Ahead | B22: [Canva link] | C22: 46366 | D22: Carousel of Podcast [Ep. #] LinkedIn IGI + Newsletter | E22: We all need to reinvent ourselves several times throughout our careers. As the year winds down, it is the perfect moment to ask whether your image still reflects where you are heading, not just where you have been. In this episode I share how to evolve your career image with intention, from updating how you present yourself to reshaping the story you tell about your experience. 🎧 Listen now [Insert podcast link] #CareerGrowth #Reinvention #PersonalBranding #Leadership | F22: Executive Presence & Image | H22: S1 Episode title + cover, S2 Hook question, S3-S5 Three key takeaways, S6 Pull quote from Jon, S7 Listen now CTA | I22: Drafted | J22: Builds on back-catalogue episode 'Reinvention and Evolution of your Career Image'. Link it in show notes.
A23: 3 Personal Brand Shifts We're Watching for 2027 | B23: [Canva link] | C23: 46371 | D23: Carousel for LinkedIn IGI + Instagram | E23: Three personal brand shifts we are watching for 2027. 1. Authenticity becomes the differentiator as AI-generated content becomes the norm. 2. Video leads on LinkedIn, rewarding leaders who are comfortable on camera. 3. Reputation outweighs reach, as trust matters more than follower counts. Which one do you think will matter most in your industry? #PersonalBranding #Trends2027 #ThoughtLeadership #LinkedIn | F23: Authentic Personal Branding | H23: S1 Title, S2 Shift 1, S3 Shift 2, S4 Shift 3, S5 Which matters most? CTA | I23: Drafted | J23: Framed as IGI's view, not a data claim.
A24: Authenticity in the Age of AI | B24: [Canva link] | C24: 46373 | D24: Carousel of Podcast [Ep. #] LinkedIn IGI + Newsletter | E24: AI can write your posts. It cannot build your reputation. With so much content now polished by the same tools, many professionals are starting to sound exactly alike. In this episode I explore why authenticity has become a genuine competitive advantage, and how to use AI as a support without losing the voice, stories and judgement that make you trusted. 🎧 Listen now [Insert podcast link] #AuthenticPersonalBranding #AI #ThoughtLeadership #PersonalBranding | F24: Authentic Personal Branding | H24: S1 Episode title + cover, S2 Hook question, S3-S5 Three key takeaways, S6 Pull quote from Jon, S7 Listen now CTA | I24: Drafted | J24: Pairs with December blog (see Content Briefs). Last newsletter before the break.
A25: Thank You for 2026 | B25: [Canva link] | C25: 46378 | D25: Carousel for LinkedIn IGI + Instagram | E25: Thank you for an incredible 2026. This year we were proud to support [NUMBER] clients across [INDUSTRIES / COUNTRIES], release [NUMBER] podcast episodes and welcome [NUMBER] new members to our community. Swipe through for a few highlights from our year. We look forward to helping you elevate your brand in 2027. #YearInReview #ThankYou #ImageGroupInternational #PersonalBranding | F25: Seasonal & Community | G25: End of year | H25: S1 Thank you 2026, S2-S5 Highlights [confirm figures], S6 See you in 2027 | I25: Drafted | J25: All figures to be confirmed by Jon before publishing. Client names only with written consent.
A26: Season's Greetings from Image Group International | B26: [Canva link] | C26: 46380 | D26: Carousel for LinkedIn IGI + Newsletter | E26: From all of us at Image Group International, thank you for being part of our community this year. To our clients, podcast listeners and everyone who has shared, commented and challenged our thinking, we are grateful. We wish you a restful festive season and a new year full of clarity and purpose. Our office will be closed from [DATE] and will reopen on [DATE]. #SeasonsGreetings #ThankYou #ImageGroupInternational | F26: Seasonal & Community | G26: Christmas Eve | H26: Single festive static graphic | I26: Drafted | J26: No new episode this week. Pre-schedule. Confirm holiday closure dates.
A27: Encore: Setting Intentional Goals for Your Personal Brand | B27: [Canva link] | C27: 46387 | D27: Carousel of Podcast (Encore) LinkedIn IGI + Newsletter | E27: Before you set your goals for 2027, decide how you want to be known. To close out the year, we are revisiting a favourite from our back catalogue. I share how to set intentional goals that align with your personal brand, so your effort in the new year builds the reputation you actually want. Happy New Year from all of us at Image Group International. 🎧 Listen now [Insert podcast link] #NewYearGoals #PersonalBranding #Intention #Leadership | F27: Authentic Personal Branding | G27: New Year's Eve | H27: S1 Episode title + cover, S2 Hook question, S3-S5 Three key takeaways, S6 Pull quote from Jon, S7 Listen now CTA | I27: Drafted | J27: Encore of existing episode 'Setting Intentional Goals for Your Personal Brand'. Pre-schedule.

Sheet Content Briefs
A1: Field | B1: October blog | C1: November blog | D1: December blog
A2: Content focus / Tentative title | B2: The Personal Brand Audit Every Leader Should Run Before Planning Season | C2: Executive Presence in a Hybrid World: How to Look as Credible on Camera as You Do in the Room | D2: Authenticity in the Age of AI: Why Your Personal Brand Matters More in 2027
A3: Due date | B3: 46308 | C3: 46336 | D3: 46364
A4: Topic summary / description | B4: A practical, step-by-step audit leaders can run in Q4 to check whether their online presence, in-person image and reputation tell the same story before next year's planning begins. Supports the 1 Oct podcast episode. | C4: Practical guidance on carrying executive presence across video calls, virtual panels and recorded content, covering lighting, framing, voice, attire and body language. Supports the 12 Nov podcast episode. | D4: An opinion-led piece on why authentic voice and reputation are becoming a competitive advantage as AI-generated content becomes widespread, with guidance on using AI as a support tool without losing credibility. Supports the 17 Dec podcast episode.
A5: Post length | B5: 1,200 to 1,500 words | C5: 1,200 to 1,500 words | D5: 1,000 to 1,300 words
A6: Target keywords | B6: personal brand audit | C6: executive presence | D6: authentic personal branding
A7: Secondary keywords | B7: personal branding for executives; LinkedIn profile review; reputation management Melbourne | C7: virtual presence tips; video call presence; image consultant Melbourne | D7: AI and personal branding; thought leadership content; LinkedIn strategy 2027
A8: Headlines / Title | B8: 1. The Personal Brand Audit Every Leader Should Run Before Planning Season 2. Is Your Personal Brand Ready for 2027? A Q4 Audit for Leaders 3. Five Questions to Audit Your Personal Brand This Quarter | C8: 1. Executive Presence in a Hybrid World 2. On Camera, On Brand: Virtual Presence for Leaders 3. How to Look as Credible on Zoom as You Do in Person | D8: 1. Authenticity in the Age of AI 2. AI Can Write Your Posts. It Cannot Build Your Reputation. 3. Why Your Personal Brand Matters More in 2027
A9: SEO description (155-160 characters) | B9: Run a personal brand audit before planning season. Learn how leaders can check that their online presence, image and reputation tell a single consistent story. | C9: Learn how to carry your executive presence into video calls and virtual events, with practical tips on lighting, framing, voice and attire for hybrid leaders. | D9: As AI-generated content becomes the norm, authenticity is a real advantage. Learn how leaders can use AI wisely without losing the voice that builds trust.
A10: SEO character count | B10: =LEN(B9) -> 159 | C10: =LEN(C9) -> 158 | D10: =LEN(D9) -> 155
A11: References | B11: [Credible sources on executive reputation and trust, to be sourced and verified] | C11: [Sources on hybrid work and virtual communication, to be sourced and verified] | D11: [Recent credible reporting on AI content adoption, to be sourced and verified]
A12: Internal links | B12: [IGI Personal Branding service page]; [Podcast episode, 1 Oct]; [Contact / consultation page] | C12: [IGI Image Consulting service page]; [Podcast episode, 12 Nov]; [Oct blog] | D12: [IGI Personal Branding service page]; [Podcast episode, 17 Dec]; [15 Dec trends carousel]
A13: Competitor articles | B13: [Top 3 ranking articles for 'personal brand audit', to research] | C13: [Top 3 ranking articles for 'executive presence virtual', to research] | D13: [Top 3 ranking articles for 'AI personal branding', to research]
A14: Product tie-in | B14: Personal brand consultation with Jon Michail [confirm current offer] | C14: Executive presence and image coaching [confirm current offer] | D14: Authority Personal Branding™ programme [confirm current offer]
A15: CTA | B15: Book a personal brand consultation to start 2027 with clarity. | C15: Speak with our team about executive presence coaching. | D15: Start 2027 with a brand that sounds like you. Book a consultation.
A16: Notes | B16: Include a downloadable checklist if design capacity allows. | C16: Use before and after framing examples. No client images without written consent. | D16: Keep Jon's point of view front and centre. Avoid unsupported statistics.
A18: Fields follow the IGI content brief template.
